Metadata-Version: 2.1
Name: pythonlibs
Version: 0.1
Summary: Repositório de aprendizado python
Home-page: https://github.com/Michel4lves/pythonlibs
Author: Michel Alves
Author-email: michelsantosa@gmail.com
License:                     GNU GENERAL PUBLIC LICENSE
Classifier: Development Status :: 2 - Pre-Alpha
Classifier: Environment :: Console
Classifier: Intended Audience :: Developers
Classifier: License :: OSI Approved :: GNU General Public License v3 (GPLv3)
Classifier: Operating System :: OS Independent
Classifier: Programming Language :: Python
Classifier: Programming Language :: Python :: 3.12
Classifier: Framework :: Pytest
License-File: LICENSE
Requires-Dist: requests
